xdsmjs
