Metadata-Version: 1.1
Name: xdsmjs
Version: 0.8.3
Summary: XDSMjs Python module
Home-page: https://github.com/OneraHub/XDSMjs
Author: Rémi Lafage
Author-email: remi.lafage@onera.fr
License: Apache License, Version 2.0
Platform: UNKNOWN
Classifier: Development Status :: 4 - Beta
Classifier: Intended Audience :: Science/Research
Classifier: Intended Audience :: Developers
Classifier: License :: OSI Approved :: Apache Software License
Classifier: Programming Language :: Python :: 3
Classifier: Topic :: Software Development
Classifier: Topic :: Scientific/Engineering
Classifier: Operating System :: Microsoft :: Windows
Classifier: Operating System :: Unix
Classifier: Operating System :: MacOS
